README.md
requirements.txt
setup.py
pieman_devices/__init__.py
pieman_devices.egg-info/PKG-INFO
pieman_devices.egg-info/SOURCES.txt
pieman_devices.egg-info/dependency_links.txt
pieman_devices.egg-info/requires.txt
pieman_devices.egg-info/top_level.txt
pieman_devices/opi-pc-plus/meta.yml
pieman_devices/opi-pc-plus/debian-buster-armhf/meta.yml
pieman_devices/opi-pc-plus/kali-rolling-armhf/meta.yml
pieman_devices/opi-zero/meta.yml
pieman_devices/opi-zero/debian-buster-armhf/meta.yml
pieman_devices/opi-zero/kali-rolling-armhf/meta.yml
pieman_devices/rpi-2-b/meta.yml
pieman_devices/rpi-2-b/alpine-3.12-armhf/meta.yml
pieman_devices/rpi-2-b/raspberrypios-buster-armhf/meta.yml
pieman_devices/rpi-2-b/ubuntu-bionic-armhf/meta.yml
pieman_devices/rpi-2-b/ubuntu-xenial-armhf/meta.yml
pieman_devices/rpi-3-b/meta.yml
pieman_devices/rpi-3-b-plus/meta.yml
pieman_devices/rpi-3-b-plus/alpine-3.12-armhf/meta.yml
pieman_devices/rpi-3-b-plus/ubuntu-bionic-armhf/meta.yml
pieman_devices/rpi-3-b-plus/ubuntu-focal-armhf/meta.yml
pieman_devices/rpi-3-b/alpine-3.12-armhf/meta.yml
pieman_devices/rpi-3-b/raspberrypios-buster-armhf/meta.yml
pieman_devices/rpi-3-b/ubuntu-bionic-arm64/meta.yml
pieman_devices/rpi-3-b/ubuntu-bionic-armhf/meta.yml
pieman_devices/rpi-4-b/meta.yml
pieman_devices/rpi-4-b/raspberrypios-buster-armhf/meta.yml
pieman_devices/rpi-b/meta.yml
pieman_devices/rpi-b/raspberrypios-buster-armhf/meta.yml
pieman_devices/rpi-zero/meta.yml
pieman_devices/rpi-zero-w/meta.yml
pieman_devices/rpi-zero-w/raspberrypios-buster-armhf/meta.yml
pieman_devices/rpi-zero/raspberrypios-buster-armhf/meta.yml