Metadata-Version: 1.2
Name: pieman-devices
Version: 0.4
Summary: Pieman devices package
Home-page: https://github.com/tolstoyevsky/pieman/tree/master/devices
Author: Evgeny Golyshev
Maintainer: Evgeny Golyshev
Maintainer-email: eugulixes@gmail.com
License: https://gnu.org/licenses/gpl-3.0.txt
Platform: UNKNOWN
